pylinal/__init__.py
pylinal/matrix.py
pylinal/py.typed
pylinal/typedefs.py
pylinal/vector.py
pylinal/functions/__init__.py
pylinal/functions/func.py
pylinal/functions/matrixfunc.py
pylinal/functions/vectorfunc.py
pylinal-0.1.5.dist-info/LICENSE
pylinal-0.1.5.dist-info/METADATA
pylinal-0.1.5.dist-info/WHEEL
pylinal-0.1.5.dist-info/top_level.txt
pylinal-0.1.5.dist-info/RECORD
