Metadata-Version: 2.1
Name: pylinal
Version: 0.1.5
Summary: Generic Linear Algebra in Python
Home-page: https://github.com/cospectrum/pylinal.git
Author: Alexey Severin
License: MIT
Keywords: python
Platform: UNKNOWN
License-File: LICENSE
